{
  "gitSyncId": "66f230eb25e8b14b5c901a19_7b02969f-64c3-4fc8-be59-6e52fd4132ac",
  "id": "listData_rll_confidential_data",
  "pluginId": "amazons3-plugin",
  "pluginType": "DB",
  "unpublishedAction": {
    "actionConfiguration": {
      "encodeParamsToggle": true,
      "formData": {
        "body": {
          "data": "{{FilePicker1.files[0]}}"
        },
        "bucket": {
          "data": "rll-confidential-data-dev"
        },
        "command": {
          "data": "UPLOAD_FILE_FROM_BODY"
        },
        "create": {
          "dataType": {
            "data": "YES"
          },
          "expiry": {
            "data": "5"
          }
        },
        "list": {
          "expiry": {
            "data": "5"
          },
          "prefix": {
            "data": ""
          },
          "signedUrl": {
            "data": "NO"
          },
          "sortBy": {
            "data": [
              {
                "column": "",
                "order": "Ascending"
              }
            ]
          },
          "unSignedUrl": {
            "data": "YES"
          },
          "where": {
            "data": {
              "children": [
                {
                  "condition": "EQ"
                }
              ],
              "condition": "AND"
            }
          }
        },
        "path": {
          "data": "{{FilePicker1.files[0].name}}"
        },
        "read": {
          "dataType": {
            "data": "YES"
          }
        },
        "smartSubstitution": {
          "data": true
        }
      },
      "paginationType": "NONE",
      "timeoutInMillisecond": 10000
    },
    "confirmBeforeExecute": false,
    "datasource": {
      "id": "REST API - Amazon S3",
      "isAutoGenerated": false,
      "name": "REST API - Amazon S3",
      "pluginId": "amazons3-plugin"
    },
    "dynamicBindingPathList": [
      {
        "key": "formData.body.data"
      },
      {
        "key": "formData.path.data"
      }
    ],
    "executeOnLoad": false,
    "name": "rll_confidential_data",
    "pageId": "listData",
    "userSetOnLoad": false
  }
}